{
    "$schema": "../../node_modules/ng-packagr/ng-package.schema.json",
    "dest": "../../dist/netgrif-components-core",
    "assets": [
        "./src/assets",
        "./src/schema/nae-schema.json"
    ],
    "lib": {
        "entryFile": "src/public-api.ts",
        "umdModuleIds": {
            "@netgrif/components-core": "@netgrif/components-core",
            "jszip": "JSZip",
            "angular-resize-event": "angularResizeEvent",
            "@covalent/core": "@covalent/core"
        }
    },
    "allowedNonPeerDependencies": ["palette-creator", "angular2-hotkeys", "tslib"]
}
